pysimplesat/__init__.py
pysimplesat/config.py
pysimplesat/exceptions.py
pysimplesat/interfaces.py
pysimplesat/py.typed
pysimplesat/types.py
pysimplesat/clients/__init__.py
pysimplesat/clients/base_client.py
pysimplesat/clients/simplesat_client.py
pysimplesat/endpoints/__init__.py
pysimplesat/endpoints/base/__init__.py
pysimplesat/endpoints/base/base_endpoint.py
pysimplesat/endpoints/simplesat/AnswersEndpoint.py
pysimplesat/endpoints/simplesat/AnswersIdEndpoint.py
pysimplesat/endpoints/simplesat/AnswersSearchEndpoint.py
pysimplesat/endpoints/simplesat/CustomersBulkEndpoint.py
pysimplesat/endpoints/simplesat/CustomersEndpoint.py
pysimplesat/endpoints/simplesat/CustomersIdEndpoint.py
pysimplesat/endpoints/simplesat/QuestionsEndpoint.py
pysimplesat/endpoints/simplesat/ResponsesCreateOrUpdateEndpoint.py
pysimplesat/endpoints/simplesat/ResponsesEndpoint.py
pysimplesat/endpoints/simplesat/ResponsesIdEndpoint.py
pysimplesat/endpoints/simplesat/ResponsesIdUpdateEndpoint.py
pysimplesat/endpoints/simplesat/ResponsesSearchEndpoint.py
pysimplesat/endpoints/simplesat/SurveysEndpoint.py
pysimplesat/endpoints/simplesat/SurveysIdEmailEndpoint.py
pysimplesat/endpoints/simplesat/SurveysIdEndpoint.py
pysimplesat/endpoints/simplesat/TeamMembersEndpoint.py
pysimplesat/endpoints/simplesat/TeamMembersIdEndpoint.py
pysimplesat/endpoints/simplesat/__init__.py
pysimplesat/models/__init__.py
pysimplesat/models/base/__init__.py
pysimplesat/models/base/base_model.py
pysimplesat/models/base/message_model.py
pysimplesat/models/simplesat/__init__.py
pysimplesat/responses/__init__.py
pysimplesat/responses/paginated_response.py
pysimplesat/utils/__init__.py
pysimplesat/utils/helpers.py
pysimplesat/utils/naming.py
pysimplesat/utils/experimental/__init__.py
pysimplesat/utils/experimental/condition.py
pysimplesat/utils/experimental/patch_maker.py
pysimplesat-0.1.10.dist-info/METADATA
pysimplesat-0.1.10.dist-info/WHEEL
pysimplesat-0.1.10.dist-info/licenses/LICENSE
pysimplesat-0.1.10.dist-info/RECORD
